setup.py
torchdv/__init__.py
torchdv/cnn_visualization.py
torchdv/cnn_visualization_using_heatmaps.py
torchdv/index.py
torchdv/invert_image_representation.py
torchdv/simple_visualization.py
torchdv/smooth_grad.py
torchdv.egg-info/PKG-INFO
torchdv.egg-info/SOURCES.txt
torchdv.egg-info/dependency_links.txt
torchdv.egg-info/top_level.txt