Metadata-Version: 1.0
Name: torchdv
Version: 0.3
Summary: Deep Visualization in pytorch
Home-page: UNKNOWN
Author: Maitreya Patel
Author-email: patel.maitreya57@gmail.com
License: UNKNOWN
Keywords: Pytorch,deep visualization,torchdv
Platform: UNKNOWN
